aiorequest/__init__.py
aiorequest/responses.py
aiorequest/sessions.py
aiorequest/types.py
aiorequest/urls.py
aiorequest-0.0.2.dist-info/AUTHORS.md
aiorequest-0.0.2.dist-info/LICENSE.md
aiorequest-0.0.2.dist-info/METADATA
aiorequest-0.0.2.dist-info/WHEEL
aiorequest-0.0.2.dist-info/top_level.txt
aiorequest-0.0.2.dist-info/RECORD
