Metadata-Version: 2.1
Name: aiorequest
Version: 0.0.2
Summary: Package provides asynchronous user-friendly HTTP client with clean objects.
Home-page: https://github.com/aiorequest/aiorequest
Author: Volodymyr Yahello
Author-email: vyahello@gmail.com
License: UNKNOWN
Platform: UNKNOWN
Classifier: Programming Language :: Python :: 3.7
Classifier: Programming Language :: Python :: 3.8
Classifier: License :: OSI Approved :: MIT License
Classifier: Operating System :: OS Independent
Requires-Python: >=3.7
Requires-Dist: attrs (==19.3.0)
Requires-Dist: bleach (==3.1.5)
Requires-Dist: certifi (==2020.4.5.1)
Requires-Dist: chardet (==3.0.4)
Requires-Dist: click (==7.1.1)
Requires-Dist: dataclasses (==0.6)
Requires-Dist: docutils (==0.16)
Requires-Dist: idna (==2.9)
Requires-Dist: keyring (==21.2.1)
Requires-Dist: packaging (==20.4)
Requires-Dist: pkginfo (==1.5.0.1)
Requires-Dist: Pygments (==2.6.1)
Requires-Dist: pyparsing (==2.4.7)
Requires-Dist: PyYAML (==5.3.1)
Requires-Dist: readme-renderer (==26.0)
Requires-Dist: requests (==2.23.0)
Requires-Dist: requests-toolbelt (==0.9.1)
Requires-Dist: six (==1.15.0)
Requires-Dist: termcolor (==1.1.0)
Requires-Dist: tqdm (==4.46.0)
Requires-Dist: twine (==3.1.1)
Requires-Dist: urllib3 (==1.25.9)
Requires-Dist: webencodings (==0.5.1)
Requires-Dist: enforce-pep8 (==0.0.8)
